{"type":"FeatureCollection","features":[{"type":"Feature","properties":{"parent_code":"5106","parent_name":"Bangli","code":"","name":"Tembuku","kind":"District"},"geometry":{"type":"Point","coordinates":[115.38809955300002,-8.417590265999962]},"id":null},{"type":"Feature","properties":{"parent_code":"5106","parent_name":"Bangli","code":"","name":"Kintamani","kind":"District"},"geometry":{"type":"Point","coordinates":[115.34534843250003,-8.249177183999961]},"id":null},{"type":"Feature","properties":{"parent_code":"5106","parent_name":"Bangli","code":"","name":"Susut","kind":"District"},"geometry":{"type":"Point","coordinates":[115.33937810900005,-8.426845692499967]},"id":null},{"type":"Feature","properties":{"parent_code":"5106","parent_name":"Bangli","code":"","name":"Bangli","kind":"District"},"geometry":{"type":"Point","coordinates":[115.36202969300007,-8.409381209999935]},"id":null}]}