{"type":"FeatureCollection","features":[{"type":"Feature","properties":{"parent_code":"2172","parent_name":"Kota Tanjung Pinang","code":"","name":"Tanjung Pinang Barat","kind":"District"},"geometry":{"type":"Point","coordinates":[104.44669534900007,0.9160290110000351]},"id":null},{"type":"Feature","properties":{"parent_code":"2172","parent_name":"Kota Tanjung Pinang","code":"","name":"Tanjung Pinang Timur","kind":"District"},"geometry":{"type":"Point","coordinates":[104.50818099500006,0.9320036305000485]},"id":null},{"type":"Feature","properties":{"parent_code":"2172","parent_name":"Kota Tanjung Pinang","code":"","name":"Tanjung Pinang Kota","kind":"District"},"geometry":{"type":"Point","coordinates":[104.41825267350006,0.957240918000053]},"id":null},{"type":"Feature","properties":{"parent_code":"2172","parent_name":"Kota Tanjung Pinang","code":"","name":"Bukit Bestari","kind":"District"},"geometry":{"type":"Point","coordinates":[104.48117340100006,0.880402412000052]},"id":null}]}