{"type":"FeatureCollection","features":[{"type":"Feature","properties":{"parent_code":"3579","parent_name":"Kota Batu","code":"","name":"Batu","kind":"District"},"geometry":{"type":"Point","coordinates":[112.51365090000007,-7.889611359499952]},"id":null},{"type":"Feature","properties":{"parent_code":"3579","parent_name":"Kota Batu","code":"","name":"Bumiaji","kind":"District"},"geometry":{"type":"Point","coordinates":[112.53961656400003,-7.8077180624999585]},"id":null},{"type":"Feature","properties":{"parent_code":"3579","parent_name":"Kota Batu","code":"","name":"Junrejo","kind":"District"},"geometry":{"type":"Point","coordinates":[112.53512495150005,-7.9074383199999545]},"id":null}]}