{"type":"FeatureCollection","features":[{"type":"Feature","properties":{"parent_code":"12--","parent_name":null,"code":"","name":null,"kind":"District"},"geometry":{"type":"Point","coordinates":[98.47240212000005,1.6193218265000555]},"id":null}]}