{"type":"FeatureCollection","features":[{"type":"Feature","properties":{"parent_code":"3575","parent_name":"Kota Pasuruan","code":"","name":"Gadingrejo","kind":"District"},"geometry":{"type":"Point","coordinates":[112.88943136300009,-7.642981380499947]},"id":null},{"type":"Feature","properties":{"parent_code":"3575","parent_name":"Kota Pasuruan","code":"","name":"Purworejo","kind":"District"},"geometry":{"type":"Point","coordinates":[112.89635666100008,-7.665117403999943]},"id":null},{"type":"Feature","properties":{"parent_code":"3575","parent_name":"Kota Pasuruan","code":"","name":"Bugul Kidul","kind":"District"},"geometry":{"type":"Point","coordinates":[112.92927667050003,-7.648243266499975]},"id":null},{"type":"Feature","properties":{"parent_code":"3575","parent_name":"Kota Pasuruan","code":"","name":"Panggungrejo","kind":"District"},"geometry":{"type":"Point","coordinates":[112.91552359000008,-7.644136165999953]},"id":null}]}