{"type":"FeatureCollection","features":[{"type":"Feature","properties":{"parent_code":"3101","parent_name":"Administrasi Kepulauan Seribu","code":"","name":"Kepulauan Seribu Selatan","kind":"District"},"geometry":{"type":"Point","coordinates":[106.66309878700005,-5.916780079999967]},"id":null},{"type":"Feature","properties":{"parent_code":"3101","parent_name":"Administrasi Kepulauan Seribu","code":"","name":"Kepulauan Seribu Utara","kind":"District"},"geometry":{"type":"Point","coordinates":[106.55202269700007,-5.487471618499967]},"id":null}]}