{"type":"FeatureCollection","features":[{"type":"Feature","properties":{"parent_code":"1375","parent_name":"Kota Bukittinggi","code":"","name":"Aur Birugo Tigo Baleh","kind":"District"},"geometry":{"type":"Point","coordinates":[100.38661147450006,-0.314740192499954]},"id":null},{"type":"Feature","properties":{"parent_code":"1375","parent_name":"Kota Bukittinggi","code":"","name":"Guguak Panjang","kind":"District"},"geometry":{"type":"Point","coordinates":[100.36571168750007,-0.30413331149995304]},"id":null},{"type":"Feature","properties":{"parent_code":"1375","parent_name":"Kota Bukittinggi","code":"","name":"Mandiangin K. Selayan","kind":"District"},"geometry":{"type":"Point","coordinates":[100.36600442600007,-0.2899228059999645]},"id":null}]}